{
  "registerUsage": "&cUse: /register <senha> <senha>",
  "registerAlready": "&cVocê ja esta registrado por favor entre utilizando: /login <senha>",
  "registerSuccess": "&eVocê esta registrado com sucesso. Guarde ou memorize sua senha para entrar novamente.",
  "registerConfirm": "&cAs duas senhas precisão ser iguais. /register <senha> <senha>",
  "alreadyLogged": "&cVocê ja esta logado.",
  "loginNotYet": "&cVocê ainda não possui uma conta por favor utilize: /register <senha> <senha>",
  "loginUsage": "&cUse: /login <senha>",
  "loginSuccess": "&eVocê entrou com sucesso!",
  "loginIncorrect": "&cSenha incorreta.",
  "loginTitle": "&ePor-favor se logue:",
  "loginSubtitle": "/login <senha>",
  "loginWelcomeTitle": "&eBem-vindo!",
  "loginWelcomeSubtitle": "Aproveite o servidor",
  "registerTitle": "&ePor-favor se registre:",
  "registerSubtitle": "/register <senha> <senha>",
  "reloadKick": "&cPor-favor re-entre em nosso servidor.",
  "timeoutKick": "&cVocê demorou muito a entrar no servidor."
}